{
  "name": "ISOMETRI CARGO VILLAGE",
  "description": "",
  "version": "1.2.0",
  "camera": {
    "eye": [
      151932.26107874242,
      -752726.0275578218,
      674897.3872391594
    ],
    "target": [
      154913.85547482336,
      253846.99682564003,
      -26633.713224262214
    ],
    "up": [
      0.0016936763292049184,
      0.571777605718378,
      0.8204069118793742
    ],
    "perspective": false,
    "fov": 35.0
  },
  "style_fog": {
    "BackgroundColor": [
      255,
      255,
      255,
      255
    ],
    "RenderMode": 2,
    "ModelTransparency": false,
    "DrawHidden": false,
    "DisplayColorByLayer": false,
    "SilhouetteWidth": 2,
    "EdgeColorMode": 1,
    "DisplayInstanceAxes": false,
    "SectionActiveColor": [
      255,
      135,
      0,
      255
    ],
    "SectionInactiveColor": [
      112,
      105,
      97,
      255
    ],
    "DisplayFog": false,
    "FogColor": [
      255,
      255,
      255,
      255
    ],
    "FogStartDist": -1.0,
    "FogEndDist": -1.0,
    "FogUseBkColor": true
  },
  "shadow_info": {
    "DisplayShadows": true,
    "Dark": 35,
    "Light": 90,
    "UseSunForAllShading": true,
    "ShadowTime": 1786013117
  },
  "env_rendering": {
    "SkyColor": [
      198,
      205,
      208,
      255
    ],
    "DrawGround": false,
    "GroundColor": [
      210,
      208,
      185,
      255
    ],
    "GroundTransparency": 50
  },
  "env_shadow": {
    "City": "Boulder (CO)",
    "Country": "USA",
    "Latitude": 40.018309,
    "Longitude": -105.242139,
    "TZOffset": -7.0,
    "DisplayNorth": false,
    "NorthAngle": 0.0
  },
  "active_section_planes": [

  ],
  "top_level_hidden": [
    {
      "persistent_id": 47299,
      "type": "Sketchup::ComponentInstance",
      "name": "",
      "definition_name": "Pola_Ruang_PDW_Detail_PL_Pemilik_Delineasi_RIB_20260511_dissolved zoning.dwg"
    }
  ],
  "visible_tags": [
    {
      "name": "Layer0",
      "visible": true
    },
    {
      "name": "ZNG - CARGO VILLAGE",
      "visible": false
    },
    {
      "name": "ZNG - CARGO VILLAGE EXT",
      "visible": false
    },
    {
      "name": "ZNG - DPPU",
      "visible": false
    },
    {
      "name": "ZNG - DPPU EXT",
      "visible": false
    },
    {
      "name": "ZNG - HND HUB",
      "visible": false
    },
    {
      "name": "ZNG - JALAN",
      "visible": true
    },
    {
      "name": "ZNG - LAHAN ALOKASI PEMERINTAH",
      "visible": false
    },
    {
      "name": "ZNG - LAHAN BUFFER",
      "visible": false
    },
    {
      "name": "ZNG - LAHAN HIJAU",
      "visible": false
    },
    {
      "name": "ZNG - LAHAN KPBU",
      "visible": false
    },
    {
      "name": "ZNG - MASJID",
      "visible": false
    },
    {
      "name": "ZNG - MRO",
      "visible": false
    },
    {
      "name": "ZNG - MRO LION",
      "visible": false
    },
    {
      "name": "ZNG - NO DATA",
      "visible": false
    },
    {
      "name": "ZNG - PERKANTORAN",
      "visible": false
    },
    {
      "name": "ZNG - SUNGAI",
      "visible": false
    },
    {
      "name": "ZNG - UTILITY VILLAGE",
      "visible": false
    },
    {
      "name": "ZNG - ZONA KOMERSIAL",
      "visible": false
    },
    {
      "name": "PL 01 - PT. Malaka Jaya Amanah",
      "visible": true
    },
    {
      "name": "PL 02 - PT. Suana Sejahtera Sentosa",
      "visible": true
    },
    {
      "name": "PL 08 - PT. Mahkota Bangun Sejahtera",
      "visible": true
    },
    {
      "name": "PL 13 - PT. Duta Bina Sejati",
      "visible": true
    },
    {
      "name": "PL 14 - PT. Tunas Sakti Mas",
      "visible": true
    },
    {
      "name": "PL 15 - PT. Perdana Propertindo Utama",
      "visible": true
    },
    {
      "name": "PL 16 - PT. Adyha Jaya Development",
      "visible": true
    },
    {
      "name": "PL 17 - PT. Batam Permata Propertindo",
      "visible": true
    },
    {
      "name": "PL 18 - PT. Limindo Properti Kabil",
      "visible": true
    },
    {
      "name": "PL 19 - PT. Batam Karya Propertindo",
      "visible": true
    },
    {
      "name": "PL 20 - PT. Aneka Nusa Land",
      "visible": true
    },
    {
      "name": "PL 22 - PT. Buana Sarana Land",
      "visible": true
    },
    {
      "name": "PL 23&24 - PT. Pandai Lintas Nusantara",
      "visible": true
    },
    {
      "name": "PL 25 - PT. Melati Segar Makmur",
      "visible": true
    },
    {
      "name": "PL 10 - PT. Gatatico Indah Persada",
      "visible": true
    },
    {
      "name": "PL 32 - PT. Sarana Bangun Sejati",
      "visible": true
    },
    {
      "name": "PL 33 - PT. Citra Tritunas Prakarsa",
      "visible": true
    },
    {
      "name": "PL 34 - PT. Limindo Putra Propertindo",
      "visible": true
    },
    {
      "name": "PL 35 - PT. Batam Prima Propertindo",
      "visible": true
    },
    {
      "name": "PL 36 - PT. Cakra Jaya Propertindo",
      "visible": true
    },
    {
      "name": "PL 3744 - PT. Prima Propertindo Utama",
      "visible": true
    },
    {
      "name": "PL 11&12 - PT. Aspen Putra Internasional",
      "visible": true
    },
    {
      "name": "RIB - SIRKULASI",
      "visible": true
    },
    {
      "name": "RIB - BANGUNAN",
      "visible": false
    },
    {
      "name": "TUPLA - PERAIRAN",
      "visible": true
    },
    {
      "name": "CTR - Contour Line",
      "visible": false
    },
    {
      "name": "CTR - Base Contour Plane",
      "visible": false
    },
    {
      "name": "CTR - DESAIN NAA",
      "visible": false
    },
    {
      "name": "PDW  - Bangunan",
      "visible": false
    },
    {
      "name": "0 Citra Drone",
      "visible": false
    },
    {
      "name": "0 Bounding Box",
      "visible": false
    },
    {
      "name": "0 Delineasi",
      "visible": false
    },
    {
      "name": "PDW - DESIGN MIX USE",
      "visible": false
    },
    {
      "name": "DESIGN SNR - MIX USE (detail)",
      "visible": true
    },
    {
      "name": "DESIGN SNR - MIX USE (massing)",
      "visible": false
    },
    {
      "name": "PDW - LRT",
      "visible": true
    },
    {
      "name": "DESIGN SNR - JALAN PDW DRAPE",
      "visible": true
    },
    {
      "name": "TERMINAL 3 - BANGUNAN",
      "visible": true
    },
    {
      "name": "0 Vegetasi",
      "visible": true
    },
    {
      "name": "TERMINAL 3 - RUNWAY",
      "visible": true
    },
    {
      "name": "F PL - Bangunan",
      "visible": true
    },
    {
      "name": "F PL - Jalan",
      "visible": true
    },
    {
      "name": "F PL - Tapak",
      "visible": true
    },
    {
      "name": "F PL - Hijau",
      "visible": true
    },
    {
      "name": "DESIGN SNR - KANTOR PENGELOLA (massing",
      "visible": true
    },
    {
      "name": "DESIGN SNR - KONTUR DELINEASI",
      "visible": false
    },
    {
      "name": "DESIGN SNR - BANGUNAN SEKITAR",
      "visible": true
    },
    {
      "name": "SAR - Versi Eksisting",
      "visible": true
    },
    {
      "name": "SAR - ROAD",
      "visible": true
    },
    {
      "name": "S1- MRO Warehouse",
      "visible": true
    },
    {
      "name": "S1 - Painting Hangar",
      "visible": true
    },
    {
      "name": "S1 - MRO Offices",
      "visible": true
    },
    {
      "name": "S1 - Public Facility",
      "visible": true
    },
    {
      "name": "S1 - Sirkulasi",
      "visible": true
    },
    {
      "name": "S2 - Sirkulasi",
      "visible": true
    },
    {
      "name": "S2 - Warehouse MRO",
      "visible": true
    },
    {
      "name": "S2 - MRO Lab",
      "visible": true
    },
    {
      "name": "S2 - Avionics Industry",
      "visible": true
    },
    {
      "name": "S1 - MRO Workshop",
      "visible": true
    },
    {
      "name": "S1 - General Hangar",
      "visible": true
    },
    {
      "name": "SAR - KONTUR SAMPING MRO",
      "visible": true
    },
    {
      "name": "DMA_AEROPARK",
      "visible": true
    },
    {
      "name": "F PL - LAYER BESAR",
      "visible": true
    },
    {
      "name": "SAR - PL SEBELAH MRO",
      "visible": true
    },
    {
      "name": "DMA_PL SELATAN",
      "visible": true
    },
    {
      "name": "DESIGN AAN - MIX USE",
      "visible": true
    },
    {
      "name": "DESIGN SNR - TERMINAL 2 RIB",
      "visible": true
    },
    {
      "name": "Versi Eksisting",
      "visible": true
    },
    {
      "name": "TERMINAL 3 - TAPAK",
      "visible": true
    },
    {
      "name": "TERMINAL 3 - JALAN",
      "visible": true
    },
    {
      "name": "pohon",
      "visible": true
    },
    {
      "name": "DESIGN CARGO VILLAGE",
      "visible": true
    },
    {
      "name": "DESIGN CARGO VILLAGE - BANGUNAN",
      "visible": false
    },
    {
      "name": "DESIGN CARGO VILLAGE - TAPAK",
      "visible": true
    },
    {
      "name": "DESIGN CARGO VILLAGE - JALAN",
      "visible": true
    },
    {
      "name": "DESIGN CARGO VILLAGE - PL SEKITAR",
      "visible": true
    }
  ],
  "axes": {
    "origin": [
      0.0,
      0.0,
      0.0
    ],
    "xaxis": [
      1.0,
      0.0,
      0.0
    ],
    "yaxis": [
      0.0,
      1.0,
      0.0
    ],
    "zaxis": [
      0.0,
      0.0,
      1.0
    ]
  },
  "viewport": {
    "width": 1387.0,
    "height": 935.0,
    "ratio": 1.483422459893048
  }
}